marqetive/__init__.py
marqetive/core/__init__.py
marqetive/core/base.py
marqetive/core/client.py
marqetive/core/exceptions.py
marqetive/core/models.py
marqetive/factory.py
marqetive/platforms/__init__.py
marqetive/platforms/instagram/__init__.py
marqetive/platforms/instagram/client.py
marqetive/platforms/instagram/exceptions.py
marqetive/platforms/instagram/media.py
marqetive/platforms/instagram/models.py
marqetive/platforms/linkedin/__init__.py
marqetive/platforms/linkedin/client.py
marqetive/platforms/linkedin/exceptions.py
marqetive/platforms/linkedin/media.py
marqetive/platforms/linkedin/models.py
marqetive/platforms/tiktok/__init__.py
marqetive/platforms/tiktok/client.py
marqetive/platforms/tiktok/exceptions.py
marqetive/platforms/tiktok/media.py
marqetive/platforms/tiktok/models.py
marqetive/platforms/twitter/__init__.py
marqetive/platforms/twitter/client.py
marqetive/platforms/twitter/exceptions.py
marqetive/platforms/twitter/media.py
marqetive/platforms/twitter/models.py
marqetive/py.typed
marqetive/utils/__init__.py
marqetive/utils/file_handlers.py
marqetive/utils/helpers.py
marqetive/utils/media.py
marqetive/utils/oauth.py
marqetive/utils/retry.py
marqetive_lib-0.2.6.dist-info/METADATA
marqetive_lib-0.2.6.dist-info/WHEEL
marqetive_lib-0.2.6.dist-info/RECORD
