Metadata-Version: 2.4
Name: marqetive-lib
Version: 0.2.6
Summary: Modern Python utilities for web APIs
Keywords: api,utilities,web,http,marqetive
Requires-Python: >=3.12
Classifier: Development Status :: 3 - Alpha
Classifier: Intended Audience :: Developers
Classifier: Programming Language :: Python :: 3
Classifier: Programming Language :: Python :: 3.12
Classifier: Programming Language :: Python :: 3.13
Classifier: Topic :: Internet :: WWW/HTTP
Classifier: Topic :: Software Development :: Libraries :: Python Modules
Provides-Extra: dev
Provides-Extra: docs
Requires-Dist: aiofiles (>=24.0.0)
Requires-Dist: httpx (>=0.28.1)
Requires-Dist: mkdocs (>=1.5.0) ; extra == "docs"
Requires-Dist: mkdocs-material (>=9.5.0) ; extra == "docs"
Requires-Dist: mkdocstrings[python] (>=0.30.1) ; extra == "docs"
Requires-Dist: pydantic (>=2.0.0)
Requires-Dist: pyright (>=1.1.0) ; extra == "dev"
Requires-Dist: pytest (>=9.0.0) ; extra == "dev"
Requires-Dist: pytest-asyncio (>=1.3.0) ; extra == "dev"
Requires-Dist: pytest-cov (>=7.0.0) ; extra == "dev"
Requires-Dist: ruff (>=0.14.4) ; extra == "dev"
Requires-Dist: tweepy (>=4.16.0,<5.0.0)
Project-URL: Documentation, https://marqetive-lib.readthedocs.io
Project-URL: Homepage, https://github.com/yourusername/marqetive-lib
Project-URL: Issues, https://github.com/yourusername/marqetive-lib/issues
Project-URL: Repository, https://github.com/yourusername/marqetive-lib
